Workbook
Name Slicer_Category: #N/A
Name Slicer_Store_Name: #N/A

Sheet HOME
A1: City Smart Retail Co.
A2: 2024 Annual Performance Dashboard
A3: Built by: Pradnya Gadhave
A19: Data Source: City Smart Retail Internal Sales System | Period: Jan–Dec 2024 |

Sheet SALES_ANALYSIS
A1: Sales Analysis — 2024
A2: Monthly trends, store performance & product rankings
A4: Month | B4: Revenue | C4: Profit | D4: MoM Growth %
A5: =PIVOT_HUB!A4 -> Jan | B5: =PIVOT_HUB!B4 -> 36202.5 | C5: =PIVOT_HUB!C4 -> 12670.875
A6: =PIVOT_HUB!A5 -> Feb | B6: =PIVOT_HUB!B5 -> 39371 | C6: =PIVOT_HUB!C5 -> 13779.85 | D6: =(B6-B5)/B5 -> 0.08752158
A7: =PIVOT_HUB!A6 -> Mar | B7: =PIVOT_HUB!B6 -> 31778 | C7: =PIVOT_HUB!C6 -> 11122.3 | D7: =(B7-B6)/B6 -> -0.19285769
A8: =PIVOT_HUB!A7 -> Apr | B8: =PIVOT_HUB!B7 -> 28303.5 | C8: =PIVOT_HUB!C7 -> 9906.225 | D8: =(B8-B7)/B7 -> -0.10933665
A9: =PIVOT_HUB!A8 -> May | B9: =PIVOT_HUB!B8 -> 35009.5 | C9: =PIVOT_HUB!C8 -> 12253.325 | D9: =(B9-B8)/B8 -> 0.23693183
A10: =PIVOT_HUB!A9 -> Jun | B10: =PIVOT_HUB!B9 -> 36761 | C10: =PIVOT_HUB!C9 -> 12866.35 | D10: =(B10-B9)/B9 -> 0.050029278
A11: =PIVOT_HUB!A10 -> Jul | B11: =PIVOT_HUB!B10 -> 22633 | C11: =PIVOT_HUB!C10 -> 7921.55 | D11: =(B11-B10)/B10 -> -0.38432034
A12: =PIVOT_HUB!A11 -> Aug | B12: =PIVOT_HUB!B11 -> 33438 | C12: =PIVOT_HUB!C11 -> 11703.3 | D12: =(B12-B11)/B11 -> 0.47740026
A13: =PIVOT_HUB!A12 -> Sep | B13: =PIVOT_HUB!B12 -> 32975.5 | C13: =PIVOT_HUB!C12 -> 11541.425 | D13: =(B13-B12)/B12 -> -0.013831569
A14: =PIVOT_HUB!A13 -> Oct | B14: =PIVOT_HUB!B13 -> 32505.5 | C14: =PIVOT_HUB!C13 -> 11376.925 | D14: =(B14-B13)/B13 -> -0.014253006
A15: =PIVOT_HUB!A14 -> Nov | B15: =PIVOT_HUB!B14 -> 16608.5 | C15: =PIVOT_HUB!C14 -> 5812.975 | D15: =(B15-B14)/B14 -> -0.4890557
A16: =PIVOT_HUB!A15 -> Dec | B16: =PIVOT_HUB!B15 -> 42428 | C16: =PIVOT_HUB!C15 -> 14849.8 | D16: =(B16-B15)/B15 -> 1.5545955
A22: Store Name | B22: Revenue | C22: Profit | D22: Profit Margin % | E22: Rank
A23: Aurangabad Square | B23: =PIVOT_HUB!G4 -> 79591.5 | C23: =PIVOT_HUB!H4 -> 27857.025 | D23: =C23/B23 -> 0.35 | E23: =RANK(B23,$B$23:$B$27,0) -> 3
A24: Mumbai Central | B24: =PIVOT_HUB!G5 -> 91990 | C24: =PIVOT_HUB!H5 -> 32196.5 | D24: =C24/B24 -> 0.35 | E24: =RANK(B24,$B$23:$B$27,0) -> 1
A25: Nagpur Hub | B25: =PIVOT_HUB!G6 -> 83293 | C25: =PIVOT_HUB!H6 -> 29152.55 | D25: =C25/B25 -> 0.35 | E25: =RANK(B25,$B$23:$B$27,0) -> 2
A26: Nashik Point | B26: =PIVOT_HUB!G7 -> 66173.5 | C26: =PIVOT_HUB!H7 -> 23160.725 | D26: =C26/B26 -> 0.35 | E26: =RANK(B26,$B$23:$B$27,0) -> 5
A27: Pune West | B27: =PIVOT_HUB!G8 -> 66966 | C27: =PIVOT_HUB!H8 -> 23438.1 | D27: =C27/B27 -> 0.35 | E27: =RANK(B27,$B$23:$B$27,0) -> 4

Sheet PIVOT_HUB
A2: Monthly Revenun | F2: Sales By Store & City
A3: Row Labels | B3: Sum of Revenue | C3: Sum of Profit | D3: Sum of Quantity | F3: Row Labels | G3: Sum of Revenue | H3: Sum of Profit
A4: Jan | B4: 36202.5 | C4: 12670.875 | D4: 65 | F4: Aurangabad Square | G4: 79591.5 | H4: 27857.025
A5: Feb | B5: 39371 | C5: 13779.85 | D5: 76 | F5: Mumbai Central | G5: 91990 | H5: 32196.5
A6: Mar | B6: 31778 | C6: 11122.3 | D6: 75 | F6: Nagpur Hub | G6: 83293 | H6: 29152.55
A7: Apr | B7: 28303.5 | C7: 9906.225 | D7: 49 | F7: Nashik Point | G7: 66173.5 | H7: 23160.725
A8: May | B8: 35009.5 | C8: 12253.325 | D8: 77 | F8: Pune West | G8: 66966 | H8: 23438.1
A9: Jun | B9: 36761 | C9: 12866.35 | D9: 76
A10: Jul | B10: 22633 | C10: 7921.55 | D10: 56
A11: Aug | B11: 33438 | C11: 11703.3 | D11: 68
A12: Sep | B12: 32975.5 | C12: 11541.425 | D12: 66
A13: Oct | B13: 32505.5 | C13: 11376.925 | D13: 57
A14: Nov | B14: 16608.5 | C14: 5812.975 | D14: 43
A15: Dec | B15: 42428 | C15: 14849.8 | D15: 84
A16: Grand Total | B16: 388014 | C16: 135804.9 | D16: 792
A18: Category Breakdown | F18: Top Products
A19: Row Labels | B19: Sum of Revenue | C19: Sum of Profit | D19: Sum of Quantity | F19: Row Labels | G19: Sum of Revenue
A20: Clothing | B20: 216966.5 | C20: 75938.275 | D20: 279 | F20: Mop Set | G20: 14163
A21: Groceries | B21: 43343.5 | C21: 15170.225 | D21: 264 | F21: Kids Hoodie | G21: 15091
A22: Home & Kitchen | B22: 127704 | C22: 44696.4 | D22: 249 | F22: Non-stick Pan | G22: 15379.5
F23: Formal Shirt | G23: 19914.5
F24: Dinner Set 12pc | G24: 23594
F25: Women's Kurta | G25: 25455
F26: Jeans Slim Fit | G26: 31137.5
F27: Pressure Cooker 3L | G27: 36806
F28: Cotton Saree | G28: 41947.5
F29: Winter Jacket | G29: 61558.5
A32: Row Labels | B32: Sum of Revenue | C32: Sum of Quantity
A33: Loyal | B33: 98181 | C33: 202
A34: New | B34: 118950 | C34: 231
A35: Returning | B35: 170883 | C35: 359

Sheet EXEC_SUMMARY
A1: City Smart Retail Co.
A2: Executive Performance Dashboard — 2024
A4: ="Total 2024 Revenue: ₹"&TEXT(B7,"##,##,##0")&" | Best Month: "&INDEX(PIVOT_HUB!A3:A14,MATCH(MAX(PIVOT_HUB!B3:B14),PIVOT_HUB!B3:B14,0)) -> Total 2024 Revenue: ₹3,88,014 | Best Month: Feb
B6: TOTAL REVENUE | D6: TOTAL PROFIT | F6: TOTAL ORDERS | H6: AVG ORDER VALUE | J6: TOP STORE | L6: TOP CATEGORY
B7: =GETPIVOTDATA("Sum of Revenue",PIVOT_HUB!$A$3) -> 388014 | D7: =GETPIVOTDATA("Sum of Profit",PIVOT_HUB!$A$3) -> 135804.9 | F7: =COUNTA(RAW_DATA!A32:A501) -> 470 | H7: =B7/F7 -> 825.5617 | J7: Mumbai Central | L7: =INDEX(PIVOT_HUB!A20:A23,MATCH(MAX(PIVOT_HUB!B20:B23),PIVOT_HUB!B20:B23,0)) -> Clothing

Sheet CUSTOMER_INSIGHTS
A1: Customer Insights — 2024
A2: RFM Analysis · Loyalty Breakdown · Basket Size
A4: Customer Type | B4: Total Orders | C4: Total Revenue | D4: Avg Order Value | E4: Avg Quantit
A5: New | B5: =COUNTIF(RAW_DATA!$H$2:$H$501,A5) -> 144 | C5: =SUMIF(RAW_DATA!$H$2:$H$501,A5,RAW_DATA!$L$2:$L$501) -> 217394 | D5: =AVERAGEIF(RAW_DATA!$H$2:$H$501,A5,RAW_DATA!$L$2:$L$501) -> 1509.6806 | E5: =AVERAGEIF(RAW_DATA!$H$2:$H$501,A5,RAW_DATA!$I$2:$I$501) -> 2.0902778
A6: Returning | B6: =COUNTIF(RAW_DATA!$H$2:$H$501,A6) -> 226 | C6: =SUMIF(RAW_DATA!$H$2:$H$501,A6,RAW_DATA!$L$2:$L$501) -> 319356 | D6: =AVERAGEIF(RAW_DATA!$H$2:$H$501,A6,RAW_DATA!$L$2:$L$501) -> 1413.0796 | E6: =AVERAGEIF(RAW_DATA!$H$2:$H$501,A6,RAW_DATA!$I$2:$I$501) -> 2.1415929
A7: Loyal | B7: =COUNTIF(RAW_DATA!$H$2:$H$501,A7) -> 130 | C7: =SUMIF(RAW_DATA!$H$2:$H$501,A7,RAW_DATA!$L$2:$L$501) -> 178483 | D7: =AVERAGEIF(RAW_DATA!$H$2:$H$501,A7,RAW_DATA!$L$2:$L$501) -> 1372.9462 | E7: =AVERAGEIF(RAW_DATA!$H$2:$H$501,A7,RAW_DATA!$I$2:$I$501) -> 2
A11: RFM Score Card
A12: Metric | B12: New | C12: Returning | D12: Loyal
A13: Recency Score | B13: =IF(B5<100,"Low",IF(B5<160,"Medium","High")) -> Medium | C13: =IF(C5<100,"Low",IF(C5<160,"Medium","High")) -> High | D13: =IF(D5<100,"Low",IF(D5<160,"Medium","High")) -> High
A14: Frequency Score | B14: =IF(B5/SUM($B$5:$B$7)<0.25,"Low",IF(B5/SUM($B$5:$B$7)<0.5,"Medium","High")) -> Medium | C14: =IF(C5/SUM($B$5:$B$7)<0.25,"Low",IF(C5/SUM($B$5:$B$7)<0.5,"Medium","High")) -> High | D14: =IF(D5/SUM($B$5:$B$7)<0.25,"Low",IF(D5/SUM($B$5:$B$7)<0.5,"Medium","High")) -> High
A15: netary Score | B15: =IF(C5<200000,"Low",IF(C5<350000,"Medium","High")) -> Medium | C15: =IF(D5<200000,"Low",IF(D5<350000,"Medium","High")) -> Low | D15: =IF(E5<200000,"Low",IF(E5<350000,"Medium","High")) -> Low
A17: Category preference per Customer Type
A18: Customer Type | B18: Electronics | C18: Clothing | D18: Groceries | E18: Home & Kitchen
A19: New | B19: =SUMIFS(RAW_DATA!$L$2:$L$501,RAW_DATA!$H$2:$H$501,A19,RAW_DATA!$E$2:$E$501,B$18) -> 98444 | C19: =SUMIFS(RAW_DATA!$L$2:$L$501,RAW_DATA!$H$2:$H$501,A19,RAW_DATA!$E$2:$E$501,C$18) -> 64462 | D19: =SUMIFS(RAW_DATA!$L$2:$L$501,RAW_DATA!$H$2:$H$501,A19,RAW_DATA!$E$2:$E$501,D$18) -> 14347 | E19: =SUMIFS(RAW_DATA!$L$2:$L$501,RAW_DATA!$H$2:$H$501,A19,RAW_DATA!$E$2:$E$501,E$18) -> 40141
A20: Returning | B20: =SUMIFS(RAW_DATA!$L$2:$L$501,RAW_DATA!$H$2:$H$501,A20,RAW_DATA!$E$2:$E$501,B$18) -> 148473 | C20: =SUMIFS(RAW_DATA!$L$2:$L$501,RAW_DATA!$H$2:$H$501,A20,RAW_DATA!$E$2:$E$501,C$18) -> 95460.5 | D20: =SUMIFS(RAW_DATA!$L$2:$L$501,RAW_DATA!$H$2:$H$501,A20,RAW_DATA!$E$2:$E$501,D$18) -> 20529 | E20: =SUMIFS(RAW_DATA!$L$2:$L$501,RAW_DATA!$H$2:$H$501,A20,RAW_DATA!$E$2:$E$501,E$18) -> 54893.5
A21: Loyal | B21: =SUMIFS(RAW_DATA!$L$2:$L$501,RAW_DATA!$H$2:$H$501,A21,RAW_DATA!$E$2:$E$501,B$18) -> 80302 | C21: =SUMIFS(RAW_DATA!$L$2:$L$501,RAW_DATA!$H$2:$H$501,A21,RAW_DATA!$E$2:$E$501,C$18) -> 57044 | D21: =SUMIFS(RAW_DATA!$L$2:$L$501,RAW_DATA!$H$2:$H$501,A21,RAW_DATA!$E$2:$E$501,D$18) -> 8467.5 | E21: =SUMIFS(RAW_DATA!$L$2:$L$501,RAW_DATA!$H$2:$H$501,A21,RAW_DATA!$E$2:$E$501,E$18) -> 32669.5

Sheet RAW_DATA
A1: Order_ID | B1: Order_Date | C1: Store_Name | D1: City | E1: Category | F1: Product_Name | G1: Customer_ID | H1: Customer_Type | I1: Quantity | J1: Unit_Price | K1: Discount_% | L1: Revenue | M1: COGS | N1: Profit
A2: ORD0249 | B2: 45293 | C2: Mumbai Central | D2: Mumbai | E2: Groceries | F2: Mixed Nuts 250g | G2: CUST0140 | H2: Returning | I2: 1 | J2: 310 | K2: 5 | L2: =I2*J2*(1-K2/100) -> 294.5 | M2: =L2*0.65 -> 191.425 | N2: =L2-M2 -> 103.075
A3: ORD0230 | B3: 45294 | C3: Aurangabad Square | D3: Aurangabad | E3: Clothing | F3: Formal Shirt | G3: CUST0122 | H3: Returning | I3: 1 | J3: 770 | K3: 10 | L3: =I3*J3*(1-K3/100) -> 693 | M3: =L3*0.65 -> 450.45 | N3: =L3-M3 -> 242.55
A4: ORD0426 | B4: 45294 | C4: Nashik Point | D4: Nashik | E4: Groceries | F4: Amul Butter 500g | G4: CUST0044 | H4: Returning | I4: 1 | J4: 260 | K4: 5 | L4: =I4*J4*(1-K4/100) -> 247 | M4: =L4*0.65 -> 160.55 | N4: =L4-M4 -> 86.45
A5: ORD0471 | B5: 45294 | C5: Nagpur Hub | D5: Nagpur | E5: Home & Kitchen | F5: Chopping Board | G5: CUST0083 | H5: Returning | I5: 3 | J5: 230 | K5: 15 | L5: =I5*J5*(1-K5/100) -> 586.5 | M5: =L5*0.65 -> 381.225 | N5: =L5-M5 -> 205.275
A6: ORD0491 | B6: 45294 | C6: Nagpur Hub | D6: Nagpur | E6: Clothing | F6: Cotton Saree | G6: CUST0165 | H6: Returning | I6: 3 | J6: 1250 | K6: 5 | L6: =I6*J6*(1-K6/100) -> 3562.5 | M6: =L6*0.65 -> 2315.625 | N6: =L6-M6 -> 1246.875
A7: ORD0033 | B7: 45296 | C7: Nashik Point | D7: Nashik | E7: Electronics | F7: Smart Watch | G7: CUST0130 | H7: New | I7: 4 | J7: 3530 | K7: 0 | L7: =I7*J7*(1-K7/100) -> 14120 | M7: =L7*0.65 -> 9178 | N7: =L7-M7 -> 4942
A8: ORD0328 | B8: 45296 | C8: Nagpur Hub | D8: Nagpur | E8: Electronics | F8: Power Bank 20000mAh | G8: CUST0123 | H8: New | I8: 1 | J8: 1040 | K8: 10 | L8: =I8*J8*(1-K8/100) -> 936 | M8: =L8*0.65 -> 608.4 | N8: =L8-M8 -> 327.6
A9: ORD0285 | B9: 45298 | C9: Nagpur Hub | D9: Nagpur | E9: Home & Kitchen | F9: Water Bottle 1L | G9: CUST0186 | H9: Loyal | I9: 4 | J9: 320 | K9: 10 | L9: =I9*J9*(1-K9/100) -> 1152 | M9: =L9*0.65 -> 748.8 | N9: =L9-M9 -> 403.2
A10: ORD0447 | B10: 45298 | C10: Aurangabad Square | D10: Aurangabad | E10: Clothing | F10: Sports Shorts | G10: CUST0177 | H10: Returning | I10: 1 | J10: 350 | K10: 15 | L10: =I10*J10*(1-K10/100) -> 297.5 | M10: =L10*0.65 -> 193.375 | N10: =L10-M10 -> 104.125
A11: ORD0060 | B11: 45302 | C11: Aurangabad Square | D11: Aurangabad | E11: Home & Kitchen | F11: Pressure Cooker 3L | G11: CUST0091 | H11: New | I11: 1 | J11: 810 | K11: 5 | L11: =I11*J11*(1-K11/100) -> 769.5 | M11: =L11*0.65 -> 500.175 | N11: =L11-M11 -> 269.325
A12: ORD0181 | B12: 45302 | C12: Nashik Point | D12: Nashik | E12: Home & Kitchen | F12: Non-stick Pan | G12: CUST0096 | H12: New | I12: 1 | J12: 720 | K12: 0 | L12: =I12*J12*(1-K12/100) -> 720 | M12: =L12*0.65 -> 468 | N12: =L12-M12 -> 252
A13: ORD0364 | B13: 45303 | C13: Mumbai Central | D13: Mumbai | E13: Clothing | F13: Winter Jacket | G13: CUST0024 | H13: Loyal | I13: 3 | J13: 1590 | K13: 15 | L13: =I13*J13*(1-K13/100) -> 4054.5 | M13: =L13*0.65 -> 2635.425 | N13: =L13-M13 -> 1419.075
... A501: ORD0227 | B501: 45657 | C501: Mumbai Central | D501: Mumbai | E501: Groceries | F501: Mixed Nuts 250g | G501: CUST0192 | H501: Returning | I501: 1 | J501: 310 | K501: 15 | L501: =I501*J501*(1-K501/100) -> 263.5 | M501: =L501*0.65 -> 171.275 | N501: =L501-M501 -> 92.225

Sheet INVENTORY
A1: Inventory Health Tracker — 2024
A2: Stock levels · Reorder alerts · Slow mover flags
A4: ="⚠️ "&COUNTIF(H6:H37,"🔴 Critical")&" products are critically low on stock. Reorder immediately." -> ⚠️ 6 products are critically low on stock. Reorder immediately.
A5: Product_Name | B5: Category | C5: Unit_Price | D5: Total_Sold | E5: Current_Stock | F5: Reorder_Point | G5: Days_of_Supply | H5: Status | I5: Stock_Value | J5: Slow_Mover | K5: Action_Required
A6: Wireless Earbuds | B6: Electronics | C6: 1899 | D6: =COUNTIF(RAW_DATA!$F$2:$F$501,A6) -> 14 | E6: 45 | F6: 20 | G6: =IFERROR(ROUND(E6/D6*30,0),"N/A") -> 96 | H6: =IF(E6<=0,"⛔ Out of Stock",IF(E6<F6,"🔴 Critical",IF(E6<F6*2,"🟡 Low","🟢 Healthy"))) -> 🟢 Healthy | I6: =E6*C6 -> 85455 | J6: =IF(D6<5,"🐢 Slow Mover","✅ Active") -> ✅ Active | K6: =IF(E6<=0,"ORDER NOW — OUT OF STOCK",IF(E6<F6,"Reorder urgently",IF(J6="🐢 Slow Mover","Review pricing","OK"))) -> OK | M6: Total Stock Value | N6: =SUM(I6:I37) -> 993333
A7: Smart Watch | B7: Electronics | C7: 3499 | D7: =COUNTIF(RAW_DATA!$F$2:$F$501,A7) -> 20 | E7: 12 | F7: 20 | G7: =IFERROR(ROUND(E7/D7*30,0),"N/A") -> 18 | H7: =IF(E7<=0,"⛔ Out of Stock",IF(E7<F7,"🔴 Critical",IF(E7<F7*2,"🟡 Low","🟢 Healthy"))) -> 🔴 Critical | I7: =E7*C7 -> 41988 | J7: =IF(D7<5,"🐢 Slow Mover","✅ Active") -> ✅ Active | K7: =IF(E7<=0,"ORDER NOW — OUT OF STOCK",IF(E7<F7,"Reorder urgently",IF(J7="🐢 Slow Mover","Review pricing","OK"))) -> Reorder urgently | M7: Critical Items | N7: =COUNTIF(H6:H37,"🔴 Critical") -> 6
A8: Bluetooth Speaker | B8: Electronics | C8: 1299 | D8: =COUNTIF(RAW_DATA!$F$2:$F$501,A8) -> 13 | E8: 78 | F8: 20 | G8: =IFERROR(ROUND(E8/D8*30,0),"N/A") -> 180 | H8: =IF(E8<=0,"⛔ Out of Stock",IF(E8<F8,"🔴 Critical",IF(E8<F8*2,"🟡 Low","🟢 Healthy"))) -> 🟢 Healthy | I8: =E8*C8 -> 101322 | J8: =IF(D8<5,"🐢 Slow Mover","✅ Active") -> ✅ Active | K8: =IF(E8<=0,"ORDER NOW — OUT OF STOCK",IF(E8<F8,"Reorder urgently",IF(J8="🐢 Slow Mover","Review pricing","OK"))) -> OK | M8: Out of Stock | N8: =COUNTIF(H6:H37,"⛔ Out of Stock") -> 0
A9: USB-C Hub | B9: Electronics | C9: 799 | D9: =COUNTIF(RAW_DATA!$F$2:$F$501,A9) -> 17 | E9: 34 | F9: 20 | G9: =IFERROR(ROUND(E9/D9*30,0),"N/A") -> 60 | H9: =IF(E9<=0,"⛔ Out of Stock",IF(E9<F9,"🔴 Critical",IF(E9<F9*2,"🟡 Low","🟢 Healthy"))) -> 🟡 Low | I9: =E9*C9 -> 27166 | J9: =IF(D9<5,"🐢 Slow Mover","✅ Active") -> ✅ Active | K9: =IF(E9<=0,"ORDER NOW — OUT OF STOCK",IF(E9<F9,"Reorder urgently",IF(J9="🐢 Slow Mover","Review pricing","OK"))) -> OK | M9: Slow Movers | N9: =COUNTIF(J6:J37,"🐢 Slow Mover") -> 0
A10: LED Desk Lamp | B10: Electronics | C10: 649 | D10: =COUNTIF(RAW_DATA!$F$2:$F$501,A10) -> 12 | E10: 56 | F10: 20 | G10: =IFERROR(ROUND(E10/D10*30,0),"N/A") -> 140 | H10: =IF(E10<=0,"⛔ Out of Stock",IF(E10<F10,"🔴 Critical",IF(E10<F10*2,"🟡 Low","🟢 Healthy"))) -> 🟢 Healthy | I10: =E10*C10 -> 36344 | J10: =IF(D10<5,"🐢 Slow Mover","✅ Active") -> ✅ Active | K10: =IF(E10<=0,"ORDER NOW — OUT OF STOCK",IF(E10<F10,"Reorder urgently",IF(J10="🐢 Slow Mover","Review pricing","OK"))) -> OK
A11: Phone Stand | B11: Electronics | C11: 349 | D11: =COUNTIF(RAW_DATA!$F$2:$F$501,A11) -> 17 | E11: 8 | F11: 20 | G11: =IFERROR(ROUND(E11/D11*30,0),"N/A") -> 14 | H11: =IF(E11<=0,"⛔ Out of Stock",IF(E11<F11,"🔴 Critical",IF(E11<F11*2,"🟡 Low","🟢 Healthy"))) -> 🔴 Critical | I11: =E11*C11 -> 2792 | J11: =IF(D11<5,"🐢 Slow Mover","✅ Active") -> ✅ Active | K11: =IF(E11<=0,"ORDER NOW — OUT OF STOCK",IF(E11<F11,"Reorder urgently",IF(J11="🐢 Slow Mover","Review pricing","OK"))) -> Reorder urgently
A12: Power Bank 20000mAh | B12: Electronics | C12: 999 | D12: =COUNTIF(RAW_DATA!$F$2:$F$501,A12) -> 16 | E12: 23 | F12: 20 | G12: =IFERROR(ROUND(E12/D12*30,0),"N/A") -> 43 | H12: =IF(E12<=0,"⛔ Out of Stock",IF(E12<F12,"🔴 Critical",IF(E12<F12*2,"🟡 Low","🟢 Healthy"))) -> 🟡 Low | I12: =E12*C12 -> 22977 | J12: =IF(D12<5,"🐢 Slow Mover","✅ Active") -> ✅ Active | K12: =IF(E12<=0,"ORDER NOW — OUT OF STOCK",IF(E12<F12,"Reorder urgently",IF(J12="🐢 Slow Mover","Review pricing","OK"))) -> OK
A13: Webcam HD | B13: Electronics | C13: 1499 | D13: =COUNTIF(RAW_DATA!$F$2:$F$501,A13) -> 8 | E13: 67 | F13: 20 | G13: =IFERROR(ROUND(E13/D13*30,0),"N/A") -> 251 | H13: =IF(E13<=0,"⛔ Out of Stock",IF(E13<F13,"🔴 Critical",IF(E13<F13*2,"🟡 Low","🟢 Healthy"))) -> 🟢 Healthy | I13: =E13*C13 -> 100433 | J13: =IF(D13<5,"🐢 Slow Mover","✅ Active") -> ✅ Active | K13: =IF(E13<=0,"ORDER NOW — OUT OF STOCK",IF(E13<F13,"Reorder urgently",IF(J13="🐢 Slow Mover","Review pricing","OK"))) -> OK
A14: Men's Polo T-Shirt | B14: Clothing | C14: 499 | D14: =COUNTIF(RAW_DATA!$F$2:$F$501,A14) -> 15 | E14: 90 | F14: 20 | G14: =IFERROR(ROUND(E14/D14*30,0),"N/A") -> 180 | H14: =IF(E14<=0,"⛔ Out of Stock",IF(E14<F14,"🔴 Critical",IF(E14<F14*2,"🟡 Low","🟢 Healthy"))) -> 🟢 Healthy | I14: =E14*C14 -> 44910 | J14: =IF(D14<5,"🐢 Slow Mover","✅ Active") -> ✅ Active | K14: =IF(E14<=0,"ORDER NOW — OUT OF STOCK",IF(E14<F14,"Reorder urgently",IF(J14="🐢 Slow Mover","Review pricing","OK"))) -> OK
A15: Women's Kurta | B15: Clothing | C15: 699 | D15: =COUNTIF(RAW_DATA!$F$2:$F$501,A15) -> 19 | E15: 15 | F15: 20 | G15: =IFERROR(ROUND(E15/D15*30,0),"N/A") -> 24 | H15: =IF(E15<=0,"⛔ Out of Stock",IF(E15<F15,"🔴 Critical",IF(E15<F15*2,"🟡 Low","🟢 Healthy"))) -> 🔴 Critical | I15: =E15*C15 -> 10485 | J15: =IF(D15<5,"🐢 Slow Mover","✅ Active") -> ✅ Active | K15: =IF(E15<=0,"ORDER NOW — OUT OF STOCK",IF(E15<F15,"Reorder urgently",IF(J15="🐢 Slow Mover","Review pricing","OK"))) -> Reorder urgently
A16: Jeans Slim Fit | B16: Clothing | C16: 899 | D16: =COUNTIF(RAW_DATA!$F$2:$F$501,A16) -> 14 | E16: 43 | F16: 20 | G16: =IFERROR(ROUND(E16/D16*30,0),"N/A") -> 92 | H16: =IF(E16<=0,"⛔ Out of Stock",IF(E16<F16,"🔴 Critical",IF(E16<F16*2,"🟡 Low","🟢 Healthy"))) -> 🟢 Healthy | I16: =E16*C16 -> 38657 | J16: =IF(D16<5,"🐢 Slow Mover","✅ Active") -> ✅ Active | K16: =IF(E16<=0,"ORDER NOW — OUT OF STOCK",IF(E16<F16,"Reorder urgently",IF(J16="🐢 Slow Mover","Review pricing","OK"))) -> OK
A17: Cotton Saree | B17: Clothing | C17: 1199 | D17: =COUNTIF(RAW_DATA!$F$2:$F$501,A17) -> 17 | E17: 28 | F17: 20 | G17: =IFERROR(ROUND(E17/D17*30,0),"N/A") -> 49 | H17: =IF(E17<=0,"⛔ Out of Stock",IF(E17<F17,"🔴 Critical",IF(E17<F17*2,"🟡 Low","🟢 Healthy"))) -> 🟡 Low | I17: =E17*C17 -> 33572 | J17: =IF(D17<5,"🐢 Slow Mover","✅ Active") -> ✅ Active | K17: =IF(E17<=0,"ORDER NOW — OUT OF STOCK",IF(E17<F17,"Reorder urgently",IF(J17="🐢 Slow Mover","Review pricing","OK"))) -> OK
A18: Kids Hoodie | B18: Clothing | C18: 599 | D18: =COUNTIF(RAW_DATA!$F$2:$F$501,A18) -> 14 | E18: 62 | F18: 20 | G18: =IFERROR(ROUND(E18/D18*30,0),"N/A") -> 133 | H18: =IF(E18<=0,"⛔ Out of Stock",IF(E18<F18,"🔴 Critical",IF(E18<F18*2,"🟡 Low","🟢 Healthy"))) -> 🟢 Healthy | I18: =E18*C18 -> 37138 | J18: =IF(D18<5,"🐢 Slow Mover","✅ Active") -> ✅ Active | K18: =IF(E18<=0,"ORDER NOW — OUT OF STOCK",IF(E18<F18,"Reorder urgently",IF(J18="🐢 Slow Mover","Review pricing","OK"))) -> OK
A19: Sports Shorts | B19: Clothing | C19: 349 | D19: =COUNTIF(RAW_DATA!$F$2:$F$501,A19) -> 13 | E19: 7 | F19: 20 | G19: =IFERROR(ROUND(E19/D19*30,0),"N/A") -> 16 | H19: =IF(E19<=0,"⛔ Out of Stock",IF(E19<F19,"🔴 Critical",IF(E19<F19*2,"🟡 Low","🟢 Healthy"))) -> 🔴 Critical | I19: =E19*C19 -> 2443 | J19: =IF(D19<5,"🐢 Slow Mover","✅ Active") -> ✅ Active | K19: =IF(E19<=0,"ORDER NOW — OUT OF STOCK",IF(E19<F19,"Reorder urgently",IF(J19="🐢 Slow Mover","Review pricing","OK"))) -> Reorder urgently
A20: Formal Shirt | B20: Clothing | C20: 749 | D20: =COUNTIF(RAW_DATA!$F$2:$F$501,A20) -> 17 | E20: 38 | F20: 20 | G20: =IFERROR(ROUND(E20/D20*30,0),"N/A") -> 67 | H20: =IF(E20<=0,"⛔ Out of Stock",IF(E20<F20,"🔴 Critical",IF(E20<F20*2,"🟡 Low","🟢 Healthy"))) -> 🟡 Low | I20: =E20*C20 -> 28462 | J20: =IF(D20<5,"🐢 Slow Mover","✅ Active") -> ✅ Active | K20: =IF(E20<=0,"ORDER NOW — OUT OF STOCK",IF(E20<F20,"Reorder urgently",IF(J20="🐢 Slow Mover","Review pricing","OK"))) -> OK
A21: Winter Jacket | B21: Clothing | C21: 1499 | D21: =COUNTIF(RAW_DATA!$F$2:$F$501,A21) -> 24 | E21: 51 | F21: 20 | G21: =IFERROR(ROUND(E21/D21*30,0),"N/A") -> 64 | H21: =IF(E21<=0,"⛔ Out of Stock",IF(E21<F21,"🔴 Critical",IF(E21<F21*2,"🟡 Low","🟢 Healthy"))) -> 🟢 Healthy | I21: =E21*C21 -> 76449 | J21: =IF(D21<5,"🐢 Slow Mover","✅ Active") -> ✅ Active | K21: =IF(E21<=0,"ORDER NOW — OUT OF STOCK",IF(E21<F21,"Reorder urgently",IF(J21="🐢 Slow Mover","Review pricing","OK"))) -> OK
... A37: Pressure Cooker 3L | B37: Home & Kitchen | C37: 899 | D37: =COUNTIF(RAW_DATA!$F$2:$F$501,A37) -> 25 | E37: 29 | F37: 20 | G37: =IFERROR(ROUND(E37/D37*30,0),"N/A") -> 35 | H37: =IF(E37<=0,"⛔ Out of Stock",IF(E37<F37,"🔴 Critical",IF(E37<F37*2,"🟡 Low","🟢 Healthy"))) -> 🟡 Low | I37: =E37*C37 -> 26071 | J37: =IF(D37<5,"🐢 Slow Mover","✅ Active") -> ✅ Active | K37: =IF(E37<=0,"ORDER NOW — OUT OF STOCK",IF(E37<F37,"Reorder urgently",IF(J37="🐢 Slow Mover","Review pricing","OK"))) -> OK

Sheet PnL
A1: Profit & Loss Statement — 2024
A2: Change assumptions in Column C to see live P&L update
A4: ASSUMPTIONS
A5: COGS % | C5: 0.69
A6: Operating Expense % | C6: 0.18
A7: Tax Rate % | C7: 0.25
A8: Discount Impact % | C8: 0.08
A9: Target Net Profit | C9: 200000
A11: P&L STATEMENT
A13: Gross Revenue | C13: =GETPIVOTDATA("Revenue",PIVOT_HUB!$A$3) -> 388014
A14: Less: Discount | C14: =-C13*C8 -> -31041.12
A15: Net Revenue | C15: =C13+C14 -> 356972.88
A16: Less: COGS | C16: =-C15*C5 -> -246311.29
A17: Gross Profit | C17: =C15+C16 -> 110661.59
A18: Gross Margin % | C18: =C17/C15 -> 0.31
A20: Operating Expenses | C20: =-C15*C6 -> -64255.118
A21: EBITDA | C21: =C17+C20 -> 46406.474
A22: EBITDA Margin % | C22: =C21/C15 -> 0.13
A24: Tax | C24: =-C21*C7 -> -11601.619
A25: Net Profit | C25: =C21+C24 -> 34804.856
A26: Net Margin % | C26: =C25/C15 -> 0.0975

Sheet STORE_COMPARISON
A1: Store Performance Comparison — 2024
A2: Weighted scoring · Head-to-head comparison · Regional rankings
A3: ="#1 Performing Store: "&INDEX($A$5:$A$9,MATCH(MAX($G$5:$G$9),$G$5:$G$9,0))&" with a weighted score of "&TEXT(MAX($G$5:$G$9),"0.0%") -> #1 Performing Store: Mumbai Central with a weighted score of 96.6%
A4: Store Name | B4: Revenue | C4: Profit | D4: Profit Margin % | E4: Orders | F4: Avg Order Value | G4: Weighted Score | H4: Final Rank | J4: Metric | K4: Weight
A5: =PIVOT_HUB!F4 -> Aurangabad Square | B5: =PIVOT_HUB!G4 -> 79591.5 | C5: =PIVOT_HUB!H4 -> 27857.025 | D5: =C5/B5 -> 0.35 | E5: =COUNTIF(RAW_DATA!$C$2:$C$501,A5) -> 117 | F5: =B5/E5 -> 680.26923 | G5: =(B5/MAX($B$5:$B$9))*$K$5+(D5/MAX($D$5:$D$9))*$K$6+(E5/MAX($E$5:$E$9))*$K$7 -> 0.94608762 | H5: =RANK(G5,$G$5:$G$9,0) -> 3 | J5: Revenue | K5: 0.4
A6: =PIVOT_HUB!F5 -> Mumbai Central | B6: =PIVOT_HUB!G5 -> 91990 | C6: =PIVOT_HUB!H5 -> 32196.5 | D6: =C6/B6 -> 0.35 | E6: =COUNTIF(RAW_DATA!$C$2:$C$501,A6) -> 101 | F6: =B6/E6 -> 910.79208 | G6: =(B6/MAX($B$5:$B$9))*$K$5+(D6/MAX($D$5:$D$9))*$K$6+(E6/MAX($E$5:$E$9))*$K$7 -> 0.96581197 | H6: =RANK(G6,$G$5:$G$9,0) -> 1 | J6: Profit Margin | K6: 0.35
A7: =PIVOT_HUB!F6 -> Nagpur Hub | B7: =PIVOT_HUB!G6 -> 83293 | C7: =PIVOT_HUB!H6 -> 29152.55 | D7: =C7/B7 -> 0.35 | E7: =COUNTIF(RAW_DATA!$C$2:$C$501,A7) -> 112 | F7: =B7/E7 -> 743.6875 | G7: =(B7/MAX($B$5:$B$9))*$K$5+(D7/MAX($D$5:$D$9))*$K$6+(E7/MAX($E$5:$E$9))*$K$7 -> 0.95149909 | H7: =RANK(G7,$G$5:$G$9,0) -> 2 | J7: Orders | K7: 0.25
A8: =PIVOT_HUB!F7 -> Nashik Point | B8: =PIVOT_HUB!G7 -> 66173.5 | C8: =PIVOT_HUB!H7 -> 23160.725 | D8: =C8/B8 -> 0.35 | E8: =COUNTIF(RAW_DATA!$C$2:$C$501,A8) -> 87 | F8: =B8/E8 -> 760.61494 | G8: =(B8/MAX($B$5:$B$9))*$K$5+(D8/MAX($D$5:$D$9))*$K$6+(E8/MAX($E$5:$E$9))*$K$7 -> 0.82363958 | H8: =RANK(G8,$G$5:$G$9,0) -> 4
A9: =PIVOT_HUB!F8 -> Pune West | B9: =PIVOT_HUB!G8 -> 66966 | C9: =PIVOT_HUB!H8 -> 23438.1 | D9: =C9/B9 -> 0.35 | E9: =COUNTIF(RAW_DATA!$C$2:$C$501,A9) -> 83 | F9: =B9/E9 -> 806.81928 | G9: =(B9/MAX($B$5:$B$9))*$K$5+(D9/MAX($D$5:$D$9))*$K$6+(E9/MAX($E$5:$E$9))*$K$7 -> 0.8185386 | H9: =RANK(G9,$G$5:$G$9,0) -> 5 | J9: Store 1 | K9: Nagpur Hub | L9: VS | M9: Store 2 | N9: Mumbai Central
J11: Metric | K11: Store 1 | M11: Srore 2
A12: Metric | B12: =A5 -> Aurangabad Square | C12: =A6 -> Mumbai Central | D12: =A7 -> Nagpur Hub | E12: =A8 -> Nashik Point | F12: =A9 -> Pune West | J12: Revenue | K12: =VLOOKUP(K9,$A$5:$H$9,2,0) -> 83293 | M12: =VLOOKUP(N9,$A$5:$H$9,2,0) -> 91990
A13: Revenue Score | B13: =B5/MAX($B$5:$B$9) -> 0.86521905 | C13: =B6/MAX($B$5:$B$9) -> 1 | D13: =B7/MAX($B$5:$B$9) -> 0.90545711 | E13: =B8/MAX($B$5:$B$9) -> 0.71935536 | F13: =B9/MAX($B$5:$B$9) -> 0.72797043 | J13: Profit Margin | K13: =VLOOKUP(K9,$A$5:$H$9,4,0) -> 0.35 | M13: =VLOOKUP(N9,$A$5:$H$9,4,0) -> 0.35
A14: Profit Margin Score | B14: =E5/MAX($E$5:$E$9) -> 1 | C14: =E6/MAX($E$5:$E$9) -> 0.86324786 | D14: =E7/MAX(E5:E9) -> 0.95726496 | E14: =E8/MAX($E$5:$E$9) -> 0.74358974 | F14: =E9/MAX($E$5:$E$9) -> 0.70940171 | J14: Orders | K14: =VLOOKUP(K9,$A$5:$H$9,5,0) -> 112 | M14: =VLOOKUP(N9,$A$5:$H$9,5,0) -> 101
A15: Order Volume Score | B15: =F5/MAX($F$5:$F$9) -> 0.74689849 | C15: =F6/MAX($F$5:$F$9) -> 1 | D15: =F7/MAX($F$5:$F$9) -> 0.81652829 | E15: =F8/MAX($F$5:$F$9) -> 0.8351137 | F15: =F9/MAX($F$5:$F$9) -> 0.88584354 | J15: Weighted Score | K15: =VLOOKUP(K9,$A$5:$H$9,7,0) -> 0.95149909 | M15: =VLOOKUP(N9,$A$5:$H$9,7,0) -> 0.96581197
A16: Avg Order Value Score | B16: =G5 -> 0.94608762 | C16: =G6 -> 0.96581197 | D16: =G7 -> 0.95149909 | E16: =G8 -> 0.82363958 | F16: =G9 -> 0.8185386 | J16: Winner | K16: =IF(K12>M12,"✅ Better","❌ Lower") -> ❌ Lower | M16: =IF(M12>K12,"✅ Better","❌ Lower") -> ✅ Better
A17: Overall Score | B17: =G5 -> 0.94608762 | C17: =G6 -> 0.96581197 | D17: =G7 -> 0.95149909 | E17: =G8 -> 0.82363958 | F17: =G9 -> 0.8185386
